[
    {
        "code": "ifrs-full_Revenue",
        "name": "매출액",
        "value": 649568305000,
        "flag": "income"
    },
    {
        "code": "ifrs-full_CostOfSales",
        "name": "매출원가",
        "value": 496094209000,
        "flag": "loss"
    },
    {
        "code": "ifrs-full_GrossProfit",
        "name": "매출총이익",
        "value": 153474096000,
        "flag": "income"
    },
    {
        "code": "dart_TotalSellingGeneralAdministrativeExpenses",
        "name": "판매비와관리비",
        "value": 121446176000,
        "flag": "loss"
    },
    {
        "code": "dart_OperatingIncomeLoss",
        "name": "영업이익(손실)",
        "value": 32027920000,
        "flag": "income"
    },
    {
        "code": "영업외이익(손실)",
        "name": "영업외이익(손실)",
        "value": 66657213000,
        "flag": "income"
    },
    {
        "code": "ifrs-full_ProfitLossBeforeTax",
        "name": "법인세비용차감전순이익(손실)",
        "value": 98685133000,
        "flag": "income"
    },
    {
        "code": "ifrs-full_IncomeTaxExpenseContinuingOperations",
        "name": "법인세비용(효익)",
        "value": 16527131000,
        "flag": "loss"
    },
    {
        "code": "ifrs-full_ProfitLoss",
        "name": "연결당기순이익(손실)",
        "value": 82158002000,
        "flag": "income"
    },
    {
        "code": "ifrs-full_OtherComprehensiveIncome",
        "name": "연결기타포괄손익",
        "value": 154052023000,
        "flag": "income"
    },
    {
        "code": "ifrs-full_ComprehensiveIncome",
        "name": "당기총포괄손익",
        "value": 236210025000,
        "flag": "income"
    }
]