[
    {
        "name": "IT서비스",
        "id": "IT서비스",
        "discretion": "mandatory",
        "value": 23814529.0,
        "children": [
            {
                "name": "삼성에스디에스",
                "id": "018260",
                "discretion": "mandatory",
                "value": [
                    13216128.0,
                    13401835.0,
                    170800,
                    173200,
                    1.41
                ]
            },
            {
                "name": "포스코DX",
                "id": "022100",
                "discretion": "mandatory",
                "value": [
                    4044124.0,
                    4006115.0,
                    26600,
                    26350,
                    -0.94
                ]
            },
            {
                "name": "카카오페이",
                "id": "377300",
                "discretion": "mandatory",
                "value": [
                    6554277.0,
                    6628603.0,
                    48500,
                    49050,
                    1.13
                ]
            }
        ]
    },
    {
        "name": "가구",
        "id": "가구",
        "discretion": "mandatory",
        "value": 1089621.0,
        "children": [
            {
                "name": "한샘",
                "id": "009240",
                "discretion": "mandatory",
                "value": [
                    1089621.0,
                    1093151.0,
                    46300,
                    46450,
                    0.32
                ]
            }
        ]
    },
    {
        "name": "가스유틸리티",
        "id": "가스유틸리티",
        "discretion": "mandatory",
        "value": 3821758.0,
        "children": [
            {
                "name": "한국가스공사",
                "id": "036460",
                "discretion": "mandatory",
                "value": [
                    3821758.0,
                    3835605.0,
                    41400,
                    41550,
                    0.36
                ]
            }
        ]
    },
    {
        "name": "가정용기기와용품",
        "id": "가정용기기와용품",
        "discretion": "mandatory",
        "value": 6392722.0,
        "children": [
            {
                "name": "코웨이",
                "id": "021240",
                "discretion": "mandatory",
                "value": [
                    6392722.0,
                    6227331.0,
                    88900,
                    86600,
                    -2.59
                ]
            }
        ]
    },
    {
        "name": "건강관리장비와용품",
        "id": "건강관리장비와용품",
        "discretion": "mandatory",
        "value": 1716701.0,
        "children": [
            {
                "name": "에스디바이오센서",
                "id": "137310",
                "discretion": "mandatory",
                "value": [
                    1144442.0,
                    1150529.0,
                    9400,
                    9450,
                    0.53
                ]
            },
            {
                "name": "덴티움",
                "id": "145720",
                "discretion": "mandatory",
                "value": [
                    572259.0,
                    572259.0,
                    51700,
                    51700,
                    0.0
                ]
            }
        ]
    },
    {
        "name": "건설",
        "id": "건설",
        "discretion": "mandatory",
        "value": 18022996.0,
        "children": [
            {
                "name": "현대건설",
                "id": "000720",
                "discretion": "mandatory",
                "value": [
                    7338345.0,
                    7639005.0,
                    65900,
                    68600,
                    4.1
                ]
            },
            {
                "name": "GS건설",
                "id": "006360",
                "discretion": "mandatory",
                "value": [
                    1628616.0,
                    1631183.0,
                    19030,
                    19060,
                    0.16
                ]
            },
            {
                "name": "HDC",
                "id": "012630",
                "discretion": "mandatory",
                "value": [
                    1058026.0,
                    1064597.0,
                    17710,
                    17820,
                    0.62
                ]
            },
            {
                "name": "삼성E&A",
                "id": "028050",
                "discretion": "mandatory",
                "value": [
                    5027400.0,
                    5056800.0,
                    25650,
                    25800,
                    0.58
                ]
            },
            {
                "name": "대우건설",
                "id": "047040",
                "discretion": "mandatory",
                "value": [
                    1442211.0,
                    1465070.0,
                    3470,
                    3525,
                    1.59
                ]
            },
            {
                "name": "DL이앤씨",
                "id": "375500",
                "discretion": "mandatory",
                "value": [
                    1528398.0,
                    1541941.0,
                    39500,
                    39850,
                    0.89
                ]
            }
        ]
    },
    {
        "name": "건축자재",
        "id": "건축자재",
        "discretion": "mandatory",
        "value": 5034834.0,
        "children": [
            {
                "name": "KCC",
                "id": "002380",
                "discretion": "mandatory",
                "value": [
                    3736761.0,
                    3905604.0,
                    420500,
                    439500,
                    4.52
                ]
            },
            {
                "name": "한일시멘트",
                "id": "300720",
                "discretion": "mandatory",
                "value": [
                    1298073.0,
                    1315724.0,
                    17650,
                    17890,
                    1.36
                ]
            }
        ]
    },
    {
        "name": "게임엔터테인먼트",
        "id": "게임엔터테인먼트",
        "discretion": "mandatory",
        "value": 22222465.0,
        "children": [
            {
                "name": "엔씨소프트",
                "id": "036570",
                "discretion": "mandatory",
                "value": [
                    4502701.0,
                    4567333.0,
                    209000,
                    212000,
                    1.44
                ]
            },
            {
                "name": "더블유게임즈",
                "id": "192080",
                "discretion": "mandatory",
                "value": [
                    1171527.0,
                    1169377.0,
                    54500,
                    54400,
                    -0.18
                ]
            },
            {
                "name": "넷마블",
                "id": "251270",
                "discretion": "mandatory",
                "value": [
                    4555536.0,
                    4581322.0,
                    53000,
                    53300,
                    0.57
                ]
            },
            {
                "name": "크래프톤",
                "id": "259960",
                "discretion": "mandatory",
                "value": [
                    11992701.0,
                    11945299.0,
                    253000,
                    252000,
                    -0.4
                ]
            }
        ]
    },
    {
        "name": "광고",
        "id": "광고",
        "discretion": "mandatory",
        "value": 2605684.0,
        "children": [
            {
                "name": "제일기획",
                "id": "030000",
                "discretion": "mandatory",
                "value": [
                    2605684.0,
                    2588428.0,
                    22650,
                    22500,
                    -0.66
                ]
            }
        ]
    },
    {
        "name": "기계",
        "id": "기계",
        "discretion": "mandatory",
        "value": 83061694.0,
        "children": [
            {
                "name": "현대엘리베이터",
                "id": "017800",
                "discretion": "mandatory",
                "value": [
                    3412765.0,
                    3541770.0,
                    87300,
                    90600,
                    3.78
                ]
            },
            {
                "name": "두산에너빌리티",
                "id": "034020",
                "discretion": "mandatory",
                "value": [
                    48042086.0,
                    49515377.0,
                    75000,
                    77300,
                    3.07
                ]
            },
            {
                "name": "HD현대인프라코어",
                "id": "042670",
                "discretion": "mandatory",
                "value": [
                    2778002.0,
                    2804441.0,
                    14710,
                    14850,
                    0.95
                ]
            },
            {
                "name": "현대로템",
                "id": "064350",
                "discretion": "mandatory",
                "value": [
                    18499619.0,
                    18947102.0,
                    169500,
                    173600,
                    2.42
                ]
            },
            {
                "name": "두산밥캣",
                "id": "241560",
                "discretion": "mandatory",
                "value": [
                    5415868.0,
                    5684265.0,
                    56500,
                    59300,
                    4.96
                ]
            },
            {
                "name": "두산로보틱스",
                "id": "454910",
                "discretion": "mandatory",
                "value": [
                    4913354.0,
                    4942523.0,
                    75800,
                    76250,
                    0.59
                ]
            }
        ]
    },
    {
        "name": "다각화된통신서비스",
        "id": "다각화된통신서비스",
        "discretion": "mandatory",
        "value": 12752297.0,
        "children": [
            {
                "name": "KT",
                "id": "030200",
                "discretion": "mandatory",
                "value": [
                    12752297.0,
                    13155532.0,
                    50600,
                    52200,
                    3.16
                ]
            }
        ]
    },
    {
        "name": "담배",
        "id": "담배",
        "discretion": "mandatory",
        "value": 17083018.0,
        "children": [
            {
                "name": "KT&G",
                "id": "033780",
                "discretion": "mandatory",
                "value": [
                    17083018.0,
                    17047625.0,
                    144800,
                    144500,
                    -0.21
                ]
            }
        ]
    },
    {
        "name": "디스플레이패널",
        "id": "디스플레이패널",
        "discretion": "mandatory",
        "value": 6255000.0,
        "children": [
            {
                "name": "LG디스플레이",
                "id": "034220",
                "discretion": "mandatory",
                "value": [
                    6255000.0,
                    6345000.0,
                    12510,
                    12690,
                    1.44
                ]
            }
        ]
    },
    {
        "name": "무선통신서비스",
        "id": "무선통신서비스",
        "discretion": "mandatory",
        "value": 17985987.0,
        "children": [
            {
                "name": "SK텔레콤",
                "id": "017670",
                "discretion": "mandatory",
                "value": [
                    11469789.0,
                    11577184.0,
                    53400,
                    53900,
                    0.94
                ]
            },
            {
                "name": "LG유플러스",
                "id": "032640",
                "discretion": "mandatory",
                "value": [
                    6516198.0,
                    6541988.0,
                    15160,
                    15220,
                    0.4
                ]
            }
        ]
    },
    {
        "name": "무역회사와판매업체",
        "id": "무역회사와판매업체",
        "discretion": "mandatory",
        "value": 9781307.0,
        "children": [
            {
                "name": "포스코인터내셔널",
                "id": "047050",
                "discretion": "mandatory",
                "value": [
                    9781307.0,
                    9710938.0,
                    55600,
                    55200,
                    -0.72
                ]
            }
        ]
    },
    {
        "name": "반도체와반도체장비",
        "id": "반도체와반도체장비",
        "discretion": "mandatory",
        "value": 1070689856.0,
        "children": [
            {
                "name": "SK하이닉스",
                "id": "000660",
                "discretion": "mandatory",
                "value": [
                    406225320.0,
                    403677311.0,
                    558000,
                    554500,
                    -0.63
                ]
            },
            {
                "name": "삼성전자",
                "id": "005930",
                "discretion": "mandatory",
                "value": [
                    612090561.0,
                    620378054.0,
                    103400,
                    104800,
                    1.35
                ]
            },
            {
                "name": "한미반도체",
                "id": "042700",
                "discretion": "mandatory",
                "value": [
                    11485120.0,
                    11609026.0,
                    120500,
                    121800,
                    1.08
                ]
            },
            {
                "name": "SK스퀘어",
                "id": "402340",
                "discretion": "mandatory",
                "value": [
                    40888855.0,
                    41816641.0,
                    308500,
                    315500,
                    2.27
                ]
            }
        ]
    },
    {
        "name": "방송과엔터테인먼트",
        "id": "방송과엔터테인먼트",
        "discretion": "mandatory",
        "value": 12682914.0,
        "children": [
            {
                "name": "하이브",
                "id": "352820",
                "discretion": "mandatory",
                "value": [
                    12682914.0,
                    12640354.0,
                    298000,
                    297000,
                    -0.34
                ]
            }
        ]
    },
    {
        "name": "백화점과일반상점",
        "id": "백화점과일반상점",
        "discretion": "mandatory",
        "value": 14558303.0,
        "children": [
            {
                "name": "신세계",
                "id": "004170",
                "discretion": "mandatory",
                "value": [
                    2300376.0,
                    2372715.0,
                    238500,
                    246000,
                    3.14
                ]
            },
            {
                "name": "GS리테일",
                "id": "007070",
                "discretion": "mandatory",
                "value": [
                    1889528.0,
                    1881167.0,
                    22600,
                    22500,
                    -0.44
                ]
            },
            {
                "name": "호텔신라",
                "id": "008770",
                "discretion": "mandatory",
                "value": [
                    1838774.0,
                    1850549.0,
                    46850,
                    47150,
                    0.64
                ]
            },
            {
                "name": "롯데쇼핑",
                "id": "023530",
                "discretion": "mandatory",
                "value": [
                    2110341.0,
                    2127314.0,
                    74600,
                    75200,
                    0.8
                ]
            },
            {
                "name": "현대백화점",
                "id": "069960",
                "discretion": "mandatory",
                "value": [
                    2228938.0,
                    2237990.0,
                    98500,
                    98900,
                    0.41
                ]
            },
            {
                "name": "이마트",
                "id": "139480",
                "discretion": "mandatory",
                "value": [
                    2268376.0,
                    2301491.0,
                    82200,
                    83400,
                    1.46
                ]
            },
            {
                "name": "BGF리테일",
                "id": "282330",
                "discretion": "mandatory",
                "value": [
                    1921970.0,
                    1932341.0,
                    111200,
                    111800,
                    0.54
                ]
            }
        ]
    },
    {
        "name": "복합기업",
        "id": "복합기업",
        "discretion": "mandatory",
        "value": 97074751.0,
        "children": [
            {
                "name": "두산",
                "id": "000150",
                "discretion": "mandatory",
                "value": [
                    13797147.0,
                    14331544.0,
                    852000,
                    885000,
                    3.87
                ]
            },
            {
                "name": "한화",
                "id": "000880",
                "discretion": "mandatory",
                "value": [
                    6019186.0,
                    6131625.0,
                    80300,
                    81800,
                    1.87
                ]
            },
            {
                "name": "CJ",
                "id": "001040",
                "discretion": "mandatory",
                "value": [
                    5149740.0,
                    5479440.0,
                    176500,
                    187800,
                    6.4
                ]
            },
            {
                "name": "LG",
                "id": "003550",
                "discretion": "mandatory",
                "value": [
                    12337727.0,
                    12615326.0,
                    80000,
                    81800,
                    2.25
                ]
            },
            {
                "name": "롯데지주",
                "id": "004990",
                "discretion": "mandatory",
                "value": [
                    2869268.0,
                    2926968.0,
                    27350,
                    27900,
                    2.01
                ]
            },
            {
                "name": "삼성물산",
                "id": "028260",
                "discretion": "mandatory",
                "value": [
                    38159734.0,
                    41814230.0,
                    224500,
                    246000,
                    9.58
                ]
            },
            {
                "name": "SK",
                "id": "034730",
                "discretion": "mandatory",
                "value": [
                    18741949.0,
                    19358222.0,
                    258500,
                    267000,
                    3.29
                ]
            }
        ]
    },
    {
        "name": "복합유틸리티",
        "id": "복합유틸리티",
        "discretion": "mandatory",
        "value": 1228505.0,
        "children": [
            {
                "name": "지역난방공사",
                "id": "071320",
                "discretion": "mandatory",
                "value": [
                    1228505.0,
                    1274820.0,
                    106100,
                    110100,
                    3.77
                ]
            }
        ]
    },
    {
        "name": "비철금속",
        "id": "비철금속",
        "discretion": "mandatory",
        "value": 28302180.0,
        "children": [
            {
                "name": "고려아연",
                "id": "010130",
                "discretion": "mandatory",
                "value": [
                    25513764.0,
                    25339675.0,
                    1319000,
                    1310000,
                    -0.68
                ]
            },
            {
                "name": "풍산",
                "id": "103140",
                "discretion": "mandatory",
                "value": [
                    2788416.0,
                    2808033.0,
                    99500,
                    100200,
                    0.7
                ]
            }
        ]
    },
    {
        "name": "상업서비스와공급품",
        "id": "상업서비스와공급품",
        "discretion": "mandatory",
        "value": 2861338.0,
        "children": [
            {
                "name": "에스원",
                "id": "012750",
                "discretion": "mandatory",
                "value": [
                    2861338.0,
                    2884138.0,
                    75300,
                    75900,
                    0.8
                ]
            }
        ]
    },
    {
        "name": "생명보험",
        "id": "생명보험",
        "discretion": "mandatory",
        "value": 33798499.0,
        "children": [
            {
                "name": "삼성생명",
                "id": "032830",
                "discretion": "mandatory",
                "value": [
                    31080000.0,
                    31180000.0,
                    155400,
                    155900,
                    0.32
                ]
            },
            {
                "name": "한화생명",
                "id": "088350",
                "discretion": "mandatory",
                "value": [
                    2718499.0,
                    2701128.0,
                    3130,
                    3110,
                    -0.64
                ]
            }
        ]
    },
    {
        "name": "석유와가스",
        "id": "석유와가스",
        "discretion": "mandatory",
        "value": 49014496.0,
        "children": [
            {
                "name": "S-Oil",
                "id": "010950",
                "discretion": "mandatory",
                "value": [
                    9096690.0,
                    9074173.0,
                    80800,
                    80600,
                    -0.25
                ]
            },
            {
                "name": "GS",
                "id": "078930",
                "discretion": "mandatory",
                "value": [
                    5351926.0,
                    5435550.0,
                    57600,
                    58500,
                    1.56
                ]
            },
            {
                "name": "SK이노베이션",
                "id": "096770",
                "discretion": "mandatory",
                "value": [
                    19525597.0,
                    19559408.0,
                    115500,
                    115700,
                    0.17
                ]
            },
            {
                "name": "HD현대",
                "id": "267250",
                "discretion": "mandatory",
                "value": [
                    15040283.0,
                    15996100.0,
                    190400,
                    202500,
                    6.36
                ]
            }
        ]
    },
    {
        "name": "섬유,의류,신발,호화품",
        "id": "섬유,의류,신발,호화품",
        "discretion": "mandatory",
        "value": 13081951.0,
        "children": [
            {
                "name": "영원무역홀딩스",
                "id": "009970",
                "discretion": "mandatory",
                "value": [
                    2446062.0,
                    2452811.0,
                    181200,
                    181700,
                    0.28
                ]
            },
            {
                "name": "미스토홀딩스",
                "id": "081660",
                "discretion": "mandatory",
                "value": [
                    2671260.0,
                    2668255.0,
                    44450,
                    44400,
                    -0.11
                ]
            },
            {
                "name": "영원무역",
                "id": "111770",
                "discretion": "mandatory",
                "value": [
                    4138691.0,
                    3979170.0,
                    93400,
                    89800,
                    -3.85
                ]
            },
            {
                "name": "효성티앤씨",
                "id": "298020",
                "discretion": "mandatory",
                "value": [
                    975892.0,
                    973728.0,
                    225500,
                    225000,
                    -0.22
                ]
            },
            {
                "name": "F&F",
                "id": "383220",
                "discretion": "mandatory",
                "value": [
                    2850046.0,
                    2807909.0,
                    74400,
                    73300,
                    -1.48
                ]
            }
        ]
    },
    {
        "name": "손해보험",
        "id": "손해보험",
        "discretion": "mandatory",
        "value": 34616774.0,
        "children": [
            {
                "name": "삼성화재",
                "id": "000810",
                "discretion": "mandatory",
                "value": [
                    22867544.0,
                    22637488.0,
                    497000,
                    492000,
                    -1.01
                ]
            },
            {
                "name": "현대해상",
                "id": "001450",
                "discretion": "mandatory",
                "value": [
                    2722230.0,
                    2737875.0,
                    30450,
                    30625,
                    0.57
                ]
            },
            {
                "name": "DB손해보험",
                "id": "005830",
                "discretion": "mandatory",
                "value": [
                    9027000.0,
                    9012840.0,
                    127500,
                    127300,
                    -0.16
                ]
            }
        ]
    },
    {
        "name": "식품",
        "id": "식품",
        "discretion": "mandatory",
        "value": 29258072.0,
        "children": [
            {
                "name": "대상",
                "id": "001680",
                "discretion": "mandatory",
                "value": [
                    729341.0,
                    734538.0,
                    21050,
                    21200,
                    0.71
                ]
            },
            {
                "name": "오리온홀딩스",
                "id": "001800",
                "discretion": "mandatory",
                "value": [
                    1241006.0,
                    1263871.0,
                    19810,
                    20175,
                    1.84
                ]
            },
            {
                "name": "삼양식품",
                "id": "003230",
                "discretion": "mandatory",
                "value": [
                    10033976.0,
                    10033976.0,
                    1332000,
                    1332000,
                    0.0
                ]
            },
            {
                "name": "농심",
                "id": "004370",
                "discretion": "mandatory",
                "value": [
                    2645949.0,
                    2630743.0,
                    435000,
                    432500,
                    -0.57
                ]
            },
            {
                "name": "동원산업",
                "id": "006040",
                "discretion": "mandatory",
                "value": [
                    1957963.0,
                    2004319.0,
                    44350,
                    45400,
                    2.37
                ]
            },
            {
                "name": "오뚜기",
                "id": "007310",
                "discretion": "mandatory",
                "value": [
                    1559046.0,
                    1567062.0,
                    389000,
                    391000,
                    0.51
                ]
            },
            {
                "name": "동서",
                "id": "026960",
                "discretion": "mandatory",
                "value": [
                    2706855.0,
                    2741750.0,
                    27150,
                    27500,
                    1.29
                ]
            },
            {
                "name": "CJ제일제당",
                "id": "097950",
                "discretion": "mandatory",
                "value": [
                    3146325.0,
                    3183960.0,
                    209000,
                    211500,
                    1.2
                ]
            },
            {
                "name": "오리온",
                "id": "271560",
                "discretion": "mandatory",
                "value": [
                    4111758.0,
                    4091990.0,
                    104000,
                    103500,
                    -0.48
                ]
            },
            {
                "name": "롯데웰푸드",
                "id": "280360",
                "discretion": "mandatory",
                "value": [
                    1125853.0,
                    1126784.0,
                    121000,
                    121100,
                    0.08
                ]
            }
        ]
    },
    {
        "name": "양방향미디어와서비스",
        "id": "양방향미디어와서비스",
        "discretion": "mandatory",
        "value": 64437048.0,
        "children": [
            {
                "name": "NAVER",
                "id": "035420",
                "discretion": "mandatory",
                "value": [
                    38115191.0,
                    38624962.0,
                    243000,
                    246250,
                    1.34
                ]
            },
            {
                "name": "카카오",
                "id": "035720",
                "discretion": "mandatory",
                "value": [
                    26321857.0,
                    26808480.0,
                    59500,
                    60600,
                    1.85
                ]
            }
        ]
    },
    {
        "name": "에너지장비및서비스",
        "id": "에너지장비및서비스",
        "discretion": "mandatory",
        "value": 6504890.0,
        "children": [
            {
                "name": "한화솔루션",
                "id": "009830",
                "discretion": "mandatory",
                "value": [
                    4744234.0,
                    4778613.0,
                    27600,
                    27800,
                    0.72
                ]
            },
            {
                "name": "씨에스윈드",
                "id": "112610",
                "discretion": "mandatory",
                "value": [
                    1760656.0,
                    1790176.0,
                    41750,
                    42450,
                    1.68
                ]
            }
        ]
    },
    {
        "name": "우주항공과국방",
        "id": "우주항공과국방",
        "discretion": "mandatory",
        "value": 71580117.0,
        "children": [
            {
                "name": "한화에어로스페이스",
                "id": "012450",
                "discretion": "mandatory",
                "value": [
                    42488242.0,
                    44550778.0,
                    824000,
                    864000,
                    4.85
                ]
            },
            {
                "name": "한국항공우주",
                "id": "047810",
                "discretion": "mandatory",
                "value": [
                    10273876.0,
                    10449331.0,
                    105400,
                    107200,
                    1.71
                ]
            },
            {
                "name": "LIG넥스원",
                "id": "079550",
                "discretion": "mandatory",
                "value": [
                    8019000.0,
                    8206000.0,
                    364500,
                    373000,
                    2.33
                ]
            },
            {
                "name": "한화시스템",
                "id": "272210",
                "discretion": "mandatory",
                "value": [
                    8605278.0,
                    8850873.0,
                    45550,
                    46850,
                    2.85
                ]
            },
            {
                "name": "한화비전",
                "id": "489790",
                "discretion": "mandatory",
                "value": [
                    2193721.0,
                    2193721.0,
                    43450,
                    43450,
                    0.0
                ]
            }
        ]
    },
    {
        "name": "은행",
        "id": "은행",
        "discretion": "mandatory",
        "value": 177664478.0,
        "children": [
            {
                "name": "기업은행",
                "id": "024110",
                "discretion": "mandatory",
                "value": [
                    16825686.0,
                    16785815.0,
                    21100,
                    21050,
                    -0.24
                ]
            },
            {
                "name": "신한지주",
                "id": "055550",
                "discretion": "mandatory",
                "value": [
                    39519288.0,
                    39033793.0,
                    81400,
                    80400,
                    -1.23
                ]
            },
            {
                "name": "하나금융지주",
                "id": "086790",
                "discretion": "mandatory",
                "value": [
                    27081102.0,
                    26886274.0,
                    97300,
                    96600,
                    -0.72
                ]
            },
            {
                "name": "KB금융",
                "id": "105560",
                "discretion": "mandatory",
                "value": [
                    50352998.0,
                    50791679.0,
                    132000,
                    133150,
                    0.87
                ]
            },
            {
                "name": "BNK금융지주",
                "id": "138930",
                "discretion": "mandatory",
                "value": [
                    4911321.0,
                    4920754.0,
                    15620,
                    15650,
                    0.19
                ]
            },
            {
                "name": "iM금융지주",
                "id": "139130",
                "discretion": "mandatory",
                "value": [
                    2364378.0,
                    2365188.0,
                    14590,
                    14595,
                    0.03
                ]
            },
            {
                "name": "JB금융지주",
                "id": "175330",
                "discretion": "mandatory",
                "value": [
                    4851552.0,
                    4756609.0,
                    25550,
                    25050,
                    -1.96
                ]
            },
            {
                "name": "우리금융지주",
                "id": "316140",
                "discretion": "mandatory",
                "value": [
                    21288213.0,
                    21067990.0,
                    29000,
                    28700,
                    -1.03
                ]
            },
            {
                "name": "카카오뱅크",
                "id": "323410",
                "discretion": "mandatory",
                "value": [
                    10469940.0,
                    10493790.0,
                    21950,
                    22000,
                    0.23
                ]
            }
        ]
    },
    {
        "name": "음료",
        "id": "음료",
        "discretion": "mandatory",
        "value": 2454744.0,
        "children": [
            {
                "name": "하이트진로",
                "id": "000080",
                "discretion": "mandatory",
                "value": [
                    1322720.0,
                    1324824.0,
                    18860,
                    18890,
                    0.16
                ]
            },
            {
                "name": "롯데칠성",
                "id": "005300",
                "discretion": "mandatory",
                "value": [
                    1132024.0,
                    1171923.0,
                    122000,
                    126300,
                    3.52
                ]
            }
        ]
    },
    {
        "name": "자동차",
        "id": "자동차",
        "discretion": "mandatory",
        "value": 100890650.0,
        "children": [
            {
                "name": "기아",
                "id": "000270",
                "discretion": "mandatory",
                "value": [
                    45678321.0,
                    46185858.0,
                    117000,
                    118300,
                    1.11
                ]
            },
            {
                "name": "KG모빌리티",
                "id": "003620",
                "discretion": "mandatory",
                "value": [
                    746763.0,
                    722478.0,
                    3690,
                    3570,
                    -3.25
                ]
            },
            {
                "name": "현대차",
                "id": "005380",
                "discretion": "mandatory",
                "value": [
                    54465566.0,
                    54567945.0,
                    266000,
                    266500,
                    0.19
                ]
            }
        ]
    },
    {
        "name": "자동차부품",
        "id": "자동차부품",
        "discretion": "mandatory",
        "value": 51641698.0,
        "children": [
            {
                "name": "한국앤컴퍼니",
                "id": "000240",
                "discretion": "mandatory",
                "value": [
                    2700908.0,
                    2715148.0,
                    28450,
                    28600,
                    0.53
                ]
            },
            {
                "name": "세방전지",
                "id": "004490",
                "discretion": "mandatory",
                "value": [
                    936600.0,
                    938000.0,
                    66900,
                    67000,
                    0.15
                ]
            },
            {
                "name": "에스엘",
                "id": "005850",
                "discretion": "mandatory",
                "value": [
                    1913679.0,
                    2062314.0,
                    41200,
                    44400,
                    7.77
                ]
            },
            {
                "name": "DN오토모티브",
                "id": "007340",
                "discretion": "mandatory",
                "value": [
                    1462772.0,
                    1456921.0,
                    25000,
                    24900,
                    -0.4
                ]
            },
            {
                "name": "현대위아",
                "id": "011210",
                "discretion": "mandatory",
                "value": [
                    1677937.0,
                    1737766.0,
                    61700,
                    63900,
                    3.57
                ]
            },
            {
                "name": "현대모비스",
                "id": "012330",
                "discretion": "mandatory",
                "value": [
                    28762229.0,
                    29170525.0,
                    317000,
                    321500,
                    1.42
                ]
            },
            {
                "name": "한온시스템",
                "id": "018880",
                "discretion": "mandatory",
                "value": [
                    2508028.0,
                    2484271.0,
                    3695,
                    3660,
                    -0.95
                ]
            },
            {
                "name": "금호타이어",
                "id": "073240",
                "discretion": "mandatory",
                "value": [
                    1700581.0,
                    1783886.0,
                    5920,
                    6210,
                    4.9
                ]
            },
            {
                "name": "한국타이어앤테크놀로지",
                "id": "161390",
                "discretion": "mandatory",
                "value": [
                    7593542.0,
                    7717417.0,
                    61300,
                    62300,
                    1.63
                ]
            },
            {
                "name": "HL만도",
                "id": "204320",
                "discretion": "mandatory",
                "value": [
                    2385422.0,
                    2498119.0,
                    50800,
                    53200,
                    4.72
                ]
            }
        ]
    },
    {
        "name": "전기유틸리티",
        "id": "전기유틸리티",
        "discretion": "mandatory",
        "value": 38500094.0,
        "children": [
            {
                "name": "한국전력",
                "id": "015760",
                "discretion": "mandatory",
                "value": [
                    32675972.0,
                    32611775.0,
                    50900,
                    50800,
                    -0.2
                ]
            },
            {
                "name": "한전KPS",
                "id": "051600",
                "discretion": "mandatory",
                "value": [
                    2380500.0,
                    2385000.0,
                    52900,
                    53000,
                    0.19
                ]
            },
            {
                "name": "한전기술",
                "id": "052690",
                "discretion": "mandatory",
                "value": [
                    3443622.0,
                    3523884.0,
                    90100,
                    92200,
                    2.33
                ]
            }
        ]
    },
    {
        "name": "전기장비",
        "id": "전기장비",
        "discretion": "mandatory",
        "value": 69450764.0,
        "children": [
            {
                "name": "대한전선",
                "id": "001440",
                "discretion": "mandatory",
                "value": [
                    4250998.0,
                    4269643.0,
                    22800,
                    22900,
                    0.44
                ]
            },
            {
                "name": "LS",
                "id": "006260",
                "discretion": "mandatory",
                "value": [
                    5518970.0,
                    5718680.0,
                    174100,
                    180400,
                    3.62
                ]
            },
            {
                "name": "LS ELECTRIC",
                "id": "010120",
                "discretion": "mandatory",
                "value": [
                    14175000.0,
                    14280000.0,
                    472500,
                    476000,
                    0.74
                ]
            },
            {
                "name": "HD현대일렉트릭",
                "id": "267260",
                "discretion": "mandatory",
                "value": [
                    28152812.0,
                    29486556.0,
                    781000,
                    818000,
                    4.74
                ]
            },
            {
                "name": "효성중공업",
                "id": "298040",
                "discretion": "mandatory",
                "value": [
                    17352984.0,
                    17632720.0,
                    1861000,
                    1891000,
                    1.61
                ]
            }
        ]
    },
    {
        "name": "전기제품",
        "id": "전기제품",
        "discretion": "mandatory",
        "value": 133414915.0,
        "children": [
            {
                "name": "삼성SDI",
                "id": "006400",
                "discretion": "mandatory",
                "value": [
                    24578587.0,
                    24417416.0,
                    305000,
                    303000,
                    -0.66
                ]
            },
            {
                "name": "엘앤에프",
                "id": "066970",
                "discretion": "mandatory",
                "value": [
                    5099587.0,
                    4981084.0,
                    129100,
                    126100,
                    -2.32
                ]
            },
            {
                "name": "SK아이이테크놀로지",
                "id": "361610",
                "discretion": "mandatory",
                "value": [
                    2416809.0,
                    2392273.0,
                    29550,
                    29250,
                    -1.02
                ]
            },
            {
                "name": "LG에너지솔루션",
                "id": "373220",
                "discretion": "mandatory",
                "value": [
                    97110000.0,
                    98163000.0,
                    415000,
                    419500,
                    1.08
                ]
            },
            {
                "name": "에코프로머티",
                "id": "450080",
                "discretion": "mandatory",
                "value": [
                    4209932.0,
                    4167972.0,
                    60200,
                    59600,
                    -1.0
                ]
            }
        ]
    },
    {
        "name": "전자장비와기기",
        "id": "전자장비와기기",
        "discretion": "mandatory",
        "value": 24692254.0,
        "children": [
            {
                "name": "삼성전기",
                "id": "009150",
                "discretion": "mandatory",
                "value": [
                    18822811.0,
                    19457708.0,
                    252000,
                    260500,
                    3.37
                ]
            },
            {
                "name": "LG이노텍",
                "id": "011070",
                "discretion": "mandatory",
                "value": [
                    5869443.0,
                    6401952.0,
                    248000,
                    270500,
                    9.07
                ]
            }
        ]
    },
    {
        "name": "전자제품",
        "id": "전자제품",
        "discretion": "mandatory",
        "value": 14203693.0,
        "children": [
            {
                "name": "LG전자",
                "id": "066570",
                "discretion": "mandatory",
                "value": [
                    14203693.0,
                    14562043.0,
                    87200,
                    89400,
                    2.52
                ]
            }
        ]
    },
    {
        "name": "제약",
        "id": "제약",
        "discretion": "mandatory",
        "value": 172247778.0,
        "children": [
            {
                "name": "유한양행",
                "id": "000100",
                "discretion": "mandatory",
                "value": [
                    9596212.0,
                    9540235.0,
                    120000,
                    119300,
                    -0.58
                ]
            },
            {
                "name": "대웅",
                "id": "003090",
                "discretion": "mandatory",
                "value": [
                    1389593.0,
                    1398315.0,
                    23900,
                    24050,
                    0.63
                ]
            },
            {
                "name": "녹십자홀딩스",
                "id": "005250",
                "discretion": "mandatory",
                "value": [
                    768441.0,
                    769852.0,
                    16340,
                    16370,
                    0.18
                ]
            },
            {
                "name": "녹십자",
                "id": "006280",
                "discretion": "mandatory",
                "value": [
                    1606899.0,
                    1604562.0,
                    137500,
                    137300,
                    -0.15
                ]
            },
            {
                "name": "한미사이언스",
                "id": "008930",
                "discretion": "mandatory",
                "value": [
                    2530487.0,
                    2530487.0,
                    37000,
                    37000,
                    0.0
                ]
            },
            {
                "name": "한올바이오파마",
                "id": "009420",
                "discretion": "mandatory",
                "value": [
                    2758306.0,
                    2685169.0,
                    52800,
                    51400,
                    -2.65
                ]
            },
            {
                "name": "삼성에피스홀딩스",
                "id": "0126Z0",
                "discretion": "mandatory",
                "value": [
                    10998308.0,
                    13785209.0,
                    442000,
                    554000,
                    25.34
                ]
            },
            {
                "name": "셀트리온",
                "id": "068270",
                "discretion": "mandatory",
                "value": [
                    42543010.0,
                    42358242.0,
                    184200,
                    183400,
                    -0.43
                ]
            },
            {
                "name": "대웅제약",
                "id": "069620",
                "discretion": "mandatory",
                "value": [
                    2086742.0,
                    2080949.0,
                    180100,
                    179600,
                    -0.28
                ]
            },
            {
                "name": "한미약품",
                "id": "128940",
                "discretion": "mandatory",
                "value": [
                    5508726.0,
                    5489510.0,
                    430000,
                    428500,
                    -0.35
                ]
            },
            {
                "name": "종근당",
                "id": "185750",
                "discretion": "mandatory",
                "value": [
                    1209124.0,
                    1202222.0,
                    87600,
                    87100,
                    -0.57
                ]
            },
            {
                "name": "삼성바이오로직스",
                "id": "207940",
                "discretion": "mandatory",
                "value": [
                    76565233.0,
                    76889270.0,
                    1654000,
                    1661000,
                    0.42
                ]
            },
            {
                "name": "SK바이오사이언스",
                "id": "302440",
                "discretion": "mandatory",
                "value": [
                    4153565.0,
                    4224097.0,
                    53000,
                    53900,
                    1.7
                ]
            },
            {
                "name": "SK바이오팜",
                "id": "326030",
                "discretion": "mandatory",
                "value": [
                    10533132.0,
                    10556626.0,
                    134500,
                    134800,
                    0.22
                ]
            }
        ]
    },
    {
        "name": "조선",
        "id": "조선",
        "discretion": "mandatory",
        "value": 139052895.0,
        "children": [
            {
                "name": "HD한국조선해양",
                "id": "009540",
                "discretion": "mandatory",
                "value": [
                    29229297.0,
                    29937028.0,
                    413000,
                    423000,
                    2.42
                ]
            },
            {
                "name": "삼성중공업",
                "id": "010140",
                "discretion": "mandatory",
                "value": [
                    21560000.0,
                    21692000.0,
                    24500,
                    24650,
                    0.61
                ]
            },
            {
                "name": "한국카본",
                "id": "017960",
                "discretion": "mandatory",
                "value": [
                    1445650.0,
                    1443055.0,
                    27850,
                    27800,
                    -0.18
                ]
            },
            {
                "name": "한화오션",
                "id": "042660",
                "discretion": "mandatory",
                "value": [
                    32510461.0,
                    32939440.0,
                    106100,
                    107500,
                    1.32
                ]
            },
            {
                "name": "HD현대중공업",
                "id": "329180",
                "discretion": "mandatory",
                "value": [
                    46162020.0,
                    47049751.0,
                    520000,
                    530000,
                    1.92
                ]
            },
            {
                "name": "HD현대마린솔루션",
                "id": "443060",
                "discretion": "mandatory",
                "value": [
                    8145467.0,
                    8369614.0,
                    181700,
                    186700,
                    2.75
                ]
            }
        ]
    },
    {
        "name": "증권",
        "id": "증권",
        "discretion": "mandatory",
        "value": 62843397.0,
        "children": [
            {
                "name": "NH투자증권",
                "id": "005940",
                "discretion": "mandatory",
                "value": [
                    7536683.0,
                    7607952.0,
                    21150,
                    21350,
                    0.95
                ]
            },
            {
                "name": "미래에셋증권",
                "id": "006800",
                "discretion": "mandatory",
                "value": [
                    12404382.0,
                    12718056.0,
                    21750,
                    22300,
                    2.53
                ]
            },
            {
                "name": "삼성증권",
                "id": "016360",
                "discretion": "mandatory",
                "value": [
                    7206510.0,
                    7313670.0,
                    80700,
                    81900,
                    1.49
                ]
            },
            {
                "name": "키움증권",
                "id": "039490",
                "discretion": "mandatory",
                "value": [
                    7389852.0,
                    7602509.0,
                    278000,
                    286000,
                    2.88
                ]
            },
            {
                "name": "한국금융지주",
                "id": "071050",
                "discretion": "mandatory",
                "value": [
                    9066619.0,
                    9205934.0,
                    162700,
                    165200,
                    1.54
                ]
            },
            {
                "name": "메리츠금융지주",
                "id": "138040",
                "discretion": "mandatory",
                "value": [
                    19239351.0,
                    19484661.0,
                    109800,
                    111200,
                    1.28
                ]
            }
        ]
    },
    {
        "name": "철강",
        "id": "철강",
        "discretion": "mandatory",
        "value": 31085288.0,
        "children": [
            {
                "name": "세아베스틸지주",
                "id": "001430",
                "discretion": "mandatory",
                "value": [
                    993381.0,
                    1013105.0,
                    27700,
                    28250,
                    1.99
                ]
            },
            {
                "name": "TCC스틸",
                "id": "002710",
                "discretion": "mandatory",
                "value": [
                    430429.0,
                    424400.0,
                    16420,
                    16190,
                    -1.4
                ]
            },
            {
                "name": "세아제강지주",
                "id": "003030",
                "discretion": "mandatory",
                "value": [
                    589772.0,
                    599298.0,
                    142400,
                    144700,
                    1.62
                ]
            },
            {
                "name": "현대제철",
                "id": "004020",
                "discretion": "mandatory",
                "value": [
                    4063424.0,
                    4050080.0,
                    30450,
                    30350,
                    -0.33
                ]
            },
            {
                "name": "POSCO홀딩스",
                "id": "005490",
                "discretion": "mandatory",
                "value": [
                    25008282.0,
                    24967816.0,
                    309000,
                    308500,
                    -0.16
                ]
            }
        ]
    },
    {
        "name": "카드",
        "id": "카드",
        "discretion": "mandatory",
        "value": 6383825.0,
        "children": [
            {
                "name": "삼성카드",
                "id": "029780",
                "discretion": "mandatory",
                "value": [
                    6383825.0,
                    6314310.0,
                    55100,
                    54500,
                    -1.09
                ]
            }
        ]
    },
    {
        "name": "포장재",
        "id": "포장재",
        "discretion": "mandatory",
        "value": 1537331.0,
        "children": [
            {
                "name": "율촌화학",
                "id": "008730",
                "discretion": "mandatory",
                "value": [
                    741520.0,
                    748960.0,
                    29900,
                    30200,
                    1.0
                ]
            },
            {
                "name": "동원시스템즈",
                "id": "014820",
                "discretion": "mandatory",
                "value": [
                    795811.0,
                    795811.0,
                    27450,
                    27450,
                    0.0
                ]
            }
        ]
    },
    {
        "name": "항공사",
        "id": "항공사",
        "discretion": "mandatory",
        "value": 15040897.0,
        "children": [
            {
                "name": "대한항공",
                "id": "003490",
                "discretion": "mandatory",
                "value": [
                    8137677.0,
                    8229732.0,
                    22100,
                    22350,
                    1.13
                ]
            },
            {
                "name": "한진칼",
                "id": "180640",
                "discretion": "mandatory",
                "value": [
                    6903220.0,
                    7056773.0,
                    103400,
                    105700,
                    2.22
                ]
            }
        ]
    },
    {
        "name": "항공화물운송과물류",
        "id": "항공화물운송과물류",
        "discretion": "mandatory",
        "value": 14835673.0,
        "children": [
            {
                "name": "CJ대한통운",
                "id": "000120",
                "discretion": "mandatory",
                "value": [
                    2130673.0,
                    2272109.0,
                    93400,
                    99600,
                    6.64
                ]
            },
            {
                "name": "현대글로비스",
                "id": "086280",
                "discretion": "mandatory",
                "value": [
                    12705000.0,
                    12712500.0,
                    169400,
                    169500,
                    0.06
                ]
            }
        ]
    },
    {
        "name": "해운사",
        "id": "해운사",
        "discretion": "mandatory",
        "value": 21347659.0,
        "children": [
            {
                "name": "HMM",
                "id": "011200",
                "discretion": "mandatory",
                "value": [
                    19006245.0,
                    18864759.0,
                    20150,
                    20000,
                    -0.74
                ]
            },
            {
                "name": "팬오션",
                "id": "028670",
                "discretion": "mandatory",
                "value": [
                    2341414.0,
                    2263902.0,
                    4380,
                    4235,
                    -3.31
                ]
            }
        ]
    },
    {
        "name": "핸드셋",
        "id": "핸드셋",
        "discretion": "mandatory",
        "value": 1289820.0,
        "children": [
            {
                "name": "영풍",
                "id": "000670",
                "discretion": "mandatory",
                "value": [
                    1289820.0,
                    1285999.0,
                    67500,
                    67300,
                    -0.3
                ]
            }
        ]
    },
    {
        "name": "호텔,레스토랑,레저",
        "id": "호텔,레스토랑,레저",
        "discretion": "mandatory",
        "value": 5540738.0,
        "children": [
            {
                "name": "강원랜드",
                "id": "035250",
                "discretion": "mandatory",
                "value": [
                    3883020.0,
                    3861626.0,
                    18150,
                    18050,
                    -0.55
                ]
            },
            {
                "name": "하나투어",
                "id": "039130",
                "discretion": "mandatory",
                "value": [
                    728027.0,
                    762105.0,
                    47000,
                    49200,
                    4.68
                ]
            },
            {
                "name": "GKL",
                "id": "114090",
                "discretion": "mandatory",
                "value": [
                    929691.0,
                    924742.0,
                    15030,
                    14950,
                    -0.53
                ]
            }
        ]
    },
    {
        "name": "화장품",
        "id": "화장품",
        "discretion": "mandatory",
        "value": 26421061.0,
        "children": [
            {
                "name": "아모레퍼시픽홀딩스",
                "id": "002790",
                "discretion": "mandatory",
                "value": [
                    2232775.0,
                    2256612.0,
                    28100,
                    28400,
                    1.07
                ]
            },
            {
                "name": "LG생활건강",
                "id": "051900",
                "discretion": "mandatory",
                "value": [
                    4223479.0,
                    4215827.0,
                    276000,
                    275500,
                    -0.18
                ]
            },
            {
                "name": "아모레퍼시픽",
                "id": "090430",
                "discretion": "mandatory",
                "value": [
                    7299896.0,
                    7317444.0,
                    124800,
                    125100,
                    0.24
                ]
            },
            {
                "name": "한국콜마",
                "id": "161890",
                "discretion": "mandatory",
                "value": [
                    1550854.0,
                    1548493.0,
                    65700,
                    65600,
                    -0.15
                ]
            },
            {
                "name": "코스맥스",
                "id": "192820",
                "discretion": "mandatory",
                "value": [
                    1849970.0,
                    1844295.0,
                    163000,
                    162500,
                    -0.31
                ]
            },
            {
                "name": "에이피알",
                "id": "278470",
                "discretion": "mandatory",
                "value": [
                    9264087.0,
                    9095649.0,
                    247500,
                    243000,
                    -1.82
                ]
            }
        ]
    },
    {
        "name": "화학",
        "id": "화학",
        "discretion": "mandatory",
        "value": 72810233.0,
        "children": [
            {
                "name": "DL",
                "id": "000210",
                "discretion": "mandatory",
                "value": [
                    820423.0,
                    826710.0,
                    39150,
                    39450,
                    0.77
                ]
            },
            {
                "name": "미원상사",
                "id": "002840",
                "discretion": "mandatory",
                "value": [
                    701100.0,
                    728175.0,
                    147600,
                    153300,
                    3.86
                ]
            },
            {
                "name": "태광산업",
                "id": "003240",
                "discretion": "mandatory",
                "value": [
                    904081.0,
                    908534.0,
                    812000,
                    816000,
                    0.49
                ]
            },
            {
                "name": "포스코퓨처엠",
                "id": "003670",
                "discretion": "mandatory",
                "value": [
                    18456341.0,
                    18189502.0,
                    207500,
                    204500,
                    -1.45
                ]
            },
            {
                "name": "롯데정밀화학",
                "id": "004000",
                "discretion": "mandatory",
                "value": [
                    1202280.0,
                    1207440.0,
                    46600,
                    46800,
                    0.43
                ]
            },
            {
                "name": "코스모화학",
                "id": "005420",
                "discretion": "mandatory",
                "value": [
                    655628.0,
                    642954.0,
                    17070,
                    16740,
                    -1.93
                ]
            },
            {
                "name": "대한유화",
                "id": "006650",
                "discretion": "mandatory",
                "value": [
                    929500.0,
                    956150.0,
                    143000,
                    147100,
                    2.87
                ]
            },
            {
                "name": "OCI홀딩스",
                "id": "010060",
                "discretion": "mandatory",
                "value": [
                    1911596.0,
                    1902497.0,
                    101600,
                    101900,
                    0.3
                ]
            },
            {
                "name": "롯데케미칼",
                "id": "011170",
                "discretion": "mandatory",
                "value": [
                    3182491.0,
                    3165381.0,
                    74400,
                    74000,
                    -0.54
                ]
            },
            {
                "name": "금호석유화학",
                "id": "011780",
                "discretion": "mandatory",
                "value": [
                    3105587.0,
                    3102984.0,
                    119300,
                    119200,
                    -0.08
                ]
            },
            {
                "name": "SKC",
                "id": "011790",
                "discretion": "mandatory",
                "value": [
                    4184447.0,
                    4207168.0,
                    110500,
                    111100,
                    0.54
                ]
            },
            {
                "name": "한솔케미칼",
                "id": "014680",
                "discretion": "mandatory",
                "value": [
                    2782790.0,
                    2777123.0,
                    245500,
                    245000,
                    -0.2
                ]
            },
            {
                "name": "LG화학",
                "id": "051910",
                "discretion": "mandatory",
                "value": [
                    26225055.0,
                    26648609.0,
                    371500,
                    377500,
                    1.62
                ]
            },
            {
                "name": "TKG휴켐스",
                "id": "069260",
                "discretion": "mandatory",
                "value": [
                    768517.0,
                    769335.0,
                    18800,
                    18820,
                    0.11
                ]
            },
            {
                "name": "후성",
                "id": "093370",
                "discretion": "mandatory",
                "value": [
                    881639.0,
                    883784.0,
                    8220,
                    8240,
                    0.24
                ]
            },
            {
                "name": "코오롱인더",
                "id": "120110",
                "discretion": "mandatory",
                "value": [
                    1180569.0,
                    1190201.0,
                    42900,
                    43250,
                    0.82
                ]
            },
            {
                "name": "미원에스씨",
                "id": "268280",
                "discretion": "mandatory",
                "value": [
                    676000.0,
                    685500.0,
                    135200,
                    137100,
                    1.41
                ]
            },
            {
                "name": "SK케미칼",
                "id": "285130",
                "discretion": "mandatory",
                "value": [
                    1245511.0,
                    1252431.0,
                    72000,
                    72400,
                    0.56
                ]
            },
            {
                "name": "HS효성첨단소재",
                "id": "298050",
                "discretion": "mandatory",
                "value": [
                    877174.0,
                    885238.0,
                    195800,
                    197600,
                    0.92
                ]
            },
            {
                "name": "OCI",
                "id": "456040",
                "discretion": "mandatory",
                "value": [
                    533569.0,
                    539835.0,
                    59600,
                    60300,
                    1.17
                ]
            },
            {
                "name": "이수스페셜티케미컬",
                "id": "457190",
                "discretion": "mandatory",
                "value": [
                    1585935.0,
                    1561768.0,
                    52500,
                    51700,
                    -1.52
                ]
            }
        ]
    }
]